webfpga/Compress.py
webfpga/Decompress.py
webfpga/Flash.py
webfpga/Synthesis.py
webfpga/__init__.py
webfpga-0.3.2.data/scripts/webfpga
webfpga-0.3.2.dist-info/LICENSE
webfpga-0.3.2.dist-info/METADATA
webfpga-0.3.2.dist-info/WHEEL
webfpga-0.3.2.dist-info/top_level.txt
webfpga-0.3.2.dist-info/RECORD
