Metadata-Version: 2.1
Name: webfpga
Version: 0.3.2
Summary: Official WebFPGA Command-line Utility
Home-page: https://github.com/webfpga/cli
Author: WebFPGA
Author-email: support@webfpga.io
License: UNKNOWN
Platform: UNKNOWN
Classifier: Programming Language :: Python :: 3
Classifier: License :: OSI Approved :: MIT License
Classifier: Operating System :: OS Independent
Requires-Dist: pyusb (>=1.0.2)
Requires-Dist: click (>=7.0)
Requires-Dist: requests (>=2.22.0)
Requires-Dist: websockets (>=8.0.2)
Requires-Dist: colorama (>=0.4.1)
Requires-Dist: termcolor (>=1.1.0)
